{
    "courseAOS": "Medicinal chemistry specialisation",
    "courseCode": "P3002",
    "courseName": "Pharmaceutical Science Advanced",
    "courseType": "Bachelor degree (honours)",
    "faculty": "Faculty of Pharmacy and Pharmaceutical Sciences",
    "teachingPeriods": [
        {
            "code": "S1-01",
            "units": [
                "PSC1011",
                "PSC1021",
                "PSC1031",
                "PSC1041"
            ],
            "year": 0
        },
        {
            "code": "S2-01",
            "units": [
                "PSC1012",
                "PSC1022",
                "PSC1032",
                "PSC1042"
            ],
            "year": 0
        },
        {
            "code": "S1-01",
            "units": [
                "PSC2011",
                "PSC2021",
                "PSC2031",
                "PSC2041"
            ],
            "year": 1
        },
        {
            "code": "S2-01",
            "units": [
                "PSC2012",
                "PSC2122",
                "PSC2132",
                "PSC2142"
            ],
            "year": 1
        },
        {
            "code": "S1-01",
            "units": [
                "PSC3111",
                "PSC3121",
                "PSC3131",
                "PSC3041"
            ],
            "year": 2
        },
        {
            "code": "S2-01",
            "units": [
                "PSC3112",
                "PSC3122",
                "PSC3432"
            ],
            "year": 2
        },
        {
            "code": "S1-01",
            "units": [
                "PSC4111"
            ],
            "year": 3
        },
        {
            "code": "S2-01",
            "units": [
                "PSC4112"
            ],
            "year": 3
        }
    ]
}